rectInspect.py
rectinspect-0.0.4.dist-info/METADATA
rectinspect-0.0.4.dist-info/WHEEL
rectinspect-0.0.4.dist-info/licenses/LICENSE
rectinspect-0.0.4.dist-info/RECORD
