Metadata-Version: 2.4
Name: rectInspect
Version: 0.0.4
Summary: rectInspect is a Python library for automated image defect detection. It allows users to detect, highlight, and manually inspect defects in images based on customizable width and height rules. You can also interactively draw rectangles on images to measure dimensions and areas. The library supports skipping certain rectangle sizes and is designed for fast, easy, and flexible inspection of defects in various types of images.
Project-URL: Homepage, https://github.com/Imesh-Isuranga/rectInspect
Project-URL: Issues, https://github.com/Imesh-Isuranga/rectInspect/issues
Author-email: Imesh Isuranga <imeshisuranga00@gmail.com>
License-File: LICENSE
Classifier: License :: OSI Approved :: GNU General Public License v3 (GPLv3)
Classifier: Operating System :: OS Independent
Classifier: Programming Language :: Python :: 3
Requires-Python: >=3.0
